framework_m_studio/__init__.py
framework_m_studio/app.py
framework_m_studio/cli.py
framework_m_studio/discovery.py
framework_m_studio/docs_generator.py
framework_m_studio/py.typed
framework_m_studio/routes.py
framework_m_studio/sdk_generator.py
framework_m_studio/workspace.py
framework_m_studio/codegen/__init__.py
framework_m_studio/codegen/generator.py
framework_m_studio/codegen/parser.py
framework_m_studio/codegen/test_generator.py
framework_m_studio/codegen/transformer.py
framework_m_studio/codegen/templates/doctype.py.jinja2
framework_m_studio/codegen/templates/test_doctype.py.jinja2
framework_m_studio/git/__init__.py
framework_m_studio/git/adapter.py
framework_m_studio/git/github_provider.py
framework_m_studio/git/protocol.py
framework_m_studio/static/favicon.ico
framework_m_studio/static/index.html
framework_m_studio/static/assets/index-BJ5Noua8.js
framework_m_studio/static/assets/index-CnPUX2YK.css
framework_m_studio-0.2.3.dist-info/METADATA
framework_m_studio-0.2.3.dist-info/WHEEL
framework_m_studio-0.2.3.dist-info/entry_points.txt
framework_m_studio-0.2.3.dist-info/RECORD
