Metadata-Version: 2.4
Name: framework-m-studio
Version: 0.2.3
Summary: Framework M Studio - Visual DocType Builder & Developer Tools
Project-URL: Homepage, https://gitlab.com/castlecraft/framework-m
Project-URL: Documentation, https://gitlab.com/castlecraft/framework-m#readme
Project-URL: Repository, https://gitlab.com/castlecraft/framework-m
Author: Framework M Contributors
License: MIT
Keywords: codegen,developer-tools,doctype,framework,studio
Classifier: Development Status :: 3 - Alpha
Classifier: Framework :: AsyncIO
Classifier: Intended Audience :: Developers
Classifier: License :: OSI Approved :: MIT License
Classifier: Programming Language :: Python :: 3
Classifier: Programming Language :: Python :: 3.12
Classifier: Programming Language :: Python :: 3.13
Classifier: Typing :: Typed
Requires-Python: >=3.12
Requires-Dist: framework-m
Requires-Dist: jinja2>=3.1.0
Requires-Dist: libcst>=1.0.0
